pcf8574_webapp/__init__.py
pcf8574_webapp/api_impl.py
pcf8574_webapp/app.py
pcf8574_webapp/jinja_filters.py
pcf8574_webapp/template_router.py
pcf8574_webapp/static/index.css
pcf8574_webapp/static/index.js
pcf8574_webapp/static/reconnecting-websocket.js
pcf8574_webapp/templates/_pin.html
pcf8574_webapp/templates/_port.html
pcf8574_webapp/templates/_table.html
pcf8574_webapp/templates/base.html
pcf8574_webapp/templates/index.html
pcf8574_webapp-0.1.2.dist-info/METADATA
pcf8574_webapp-0.1.2.dist-info/WHEEL
pcf8574_webapp-0.1.2.dist-info/licenses/LICENSE
pcf8574_webapp-0.1.2.dist-info/RECORD
