Metadata-Version: 2.4
Name: pcf8574_webapp
Version: 0.1.2
Summary: This is a Python library designed to be able to easily control your PCF8574 I/O expanders over a Web interface.
Project-URL: Repository, https://codeberg.org/Foerderverein_DresdnerParkeisenbahn_eV/pcf8574_webapp
Author-email: Timo Klinge <kl.timo@outlook.de>
License-Expression: MIT
License-File: LICENSE
Classifier: Operating System :: OS Independent
Classifier: Programming Language :: Python :: 3
Requires-Python: >=3.7
Requires-Dist: fastapi~=0.115.12
Requires-Dist: jinja2~=3.1.6
Requires-Dist: pcf8574-interface~=1.1.0
Requires-Dist: uvicorn~=0.34.3
